lockex/__init__.py
lockex/execute.py
lockex/glog.py
lockex-0.3.dist-info/DESCRIPTION.rst
lockex-0.3.dist-info/METADATA
lockex-0.3.dist-info/RECORD
lockex-0.3.dist-info/WHEEL
lockex-0.3.dist-info/entry_points.txt
lockex-0.3.dist-info/metadata.json
lockex-0.3.dist-info/top_level.txt
