Metadata-Version: 2.0
Name: lockex
Version: 0.3
Summary: Get lock from zookeeper and execute
Home-page: UNKNOWN
Author: UNKNOWN
Author-email: UNKNOWN
License: BSD
Platform: UNKNOWN
Requires-Dist: click (==6.2)
Requires-Dist: future (==0.15.2)
Requires-Dist: kazoo (==2.2.1)
Requires-Dist: psutil (==4.1.0)
Requires-Dist: python-gflags (==2.0)
Provides-Extra: test
Requires-Dist: testfixtures; extra == 'test'
